Metadata-Version: 1.1
Name: comparator
Version: 0.4.0
Summary: Utility for comparing results between data sources
Home-page: https://github.com/aaronbiller/comparator
Author: Aaron Biller
Author-email: aaronbiller@gmail.com
License: Apache 2.0
Keywords: utility compare database
Platform: UNKNOWN
Classifier: Development Status :: 3 - Alpha
Classifier: Intended Audience :: Developers
Classifier: Programming Language :: Python :: 2
Classifier: Programming Language :: Python :: 2.7
Classifier: Programming Language :: Python :: 3
Classifier: Programming Language :: Python :: 3.6
Classifier: Programming Language :: Python :: 3.7
Classifier: Topic :: Database
Classifier: Topic :: Utilities
